pymedio/__init__.py
pymedio/base.py
pymedio/dicom.py
pymedio/exceptions.py
pymedio/functional.py
pymedio/image.py
pymedio/py.typed
pymedio/typing.py
pymedio/utils.py
pymedio-0.2.14.dist-info/LICENSE
pymedio-0.2.14.dist-info/METADATA
pymedio-0.2.14.dist-info/WHEEL
pymedio-0.2.14.dist-info/top_level.txt
pymedio-0.2.14.dist-info/RECORD
