Metadata-Version: 2.1
Name: pymedio
Version: 0.2.14
Summary: read arbitrary medical images in python
Home-page: https://github.com/jcreinhold/pymedio
Author: Jacob Reinhold
Author-email: jcreinhold@gmail.com
License: MIT license
Project-URL: Bug Tracker, https://github.com/jcreinhold/pymedio/issues
Project-URL: Documentation, https://pymedio.readthedocs.io/
Keywords: pymedio
Classifier: Development Status :: 2 - Pre-Alpha
Classifier: Intended Audience :: Developers
Classifier: License :: OSI Approved :: MIT License
Classifier: Natural Language :: English
Classifier: Programming Language :: Python :: 3
Classifier: Programming Language :: Python :: 3 :: Only
Classifier: Programming Language :: Python :: Implementation :: CPython
Classifier: Typing :: Typed
Requires-Python: >=3.9
License-File: LICENSE
Requires-Dist: numpy (>=1.22)
Provides-Extra: all
Requires-Dist: SimpleITK (>=2.1.0) ; extra == 'all'
Requires-Dist: cryptography (>=36.0) ; extra == 'all'
Requires-Dist: nibabel (>=3) ; extra == 'all'
Requires-Dist: pydicom (>=2) ; extra == 'all'
Provides-Extra: cryptography
Requires-Dist: cryptography (>=36.0) ; extra == 'cryptography'
Provides-Extra: dicom
Requires-Dist: pydicom (>=2) ; extra == 'dicom'
